odoo8_addon_crm_phonecall_category-8.0.1.0.0.99.dev20-py2.7-nspkg.pth
odoo8_addon_crm_phonecall_category-8.0.1.0.0.99.dev20.dist-info/METADATA
odoo8_addon_crm_phonecall_category-8.0.1.0.0.99.dev20.dist-info/RECORD
odoo8_addon_crm_phonecall_category-8.0.1.0.0.99.dev20.dist-info/WHEEL
odoo8_addon_crm_phonecall_category-8.0.1.0.0.99.dev20.dist-info/namespace_packages.txt
odoo8_addon_crm_phonecall_category-8.0.1.0.0.99.dev20.dist-info/top_level.txt
odoo_addons/crm_phonecall_category/README.rst
odoo_addons/crm_phonecall_category/__init__.py
odoo_addons/crm_phonecall_category/__openerp__.py
odoo_addons/crm_phonecall_category/i18n/ar.po
odoo_addons/crm_phonecall_category/i18n/bg.po
odoo_addons/crm_phonecall_category/i18n/bs.po
odoo_addons/crm_phonecall_category/i18n/crm_phonecall_category.pot
odoo_addons/crm_phonecall_category/i18n/cs.po
odoo_addons/crm_phonecall_category/i18n/da.po
odoo_addons/crm_phonecall_category/i18n/de.po
odoo_addons/crm_phonecall_category/i18n/en_GB.po
odoo_addons/crm_phonecall_category/i18n/es.po
odoo_addons/crm_phonecall_category/i18n/es_AR.po
odoo_addons/crm_phonecall_category/i18n/es_CL.po
odoo_addons/crm_phonecall_category/i18n/es_CO.po
odoo_addons/crm_phonecall_category/i18n/es_CR.po
odoo_addons/crm_phonecall_category/i18n/es_DO.po
odoo_addons/crm_phonecall_category/i18n/es_EC.po
odoo_addons/crm_phonecall_category/i18n/es_MX.po
odoo_addons/crm_phonecall_category/i18n/es_PE.po
odoo_addons/crm_phonecall_category/i18n/es_PY.po
odoo_addons/crm_phonecall_category/i18n/es_VE.po
odoo_addons/crm_phonecall_category/i18n/et.po
odoo_addons/crm_phonecall_category/i18n/eu.po
odoo_addons/crm_phonecall_category/i18n/fa.po
odoo_addons/crm_phonecall_category/i18n/fr.po
odoo_addons/crm_phonecall_category/i18n/fr_CH.po
odoo_addons/crm_phonecall_category/i18n/gl.po
odoo_addons/crm_phonecall_category/i18n/he.po
odoo_addons/crm_phonecall_category/i18n/hr.po
odoo_addons/crm_phonecall_category/i18n/hu.po
odoo_addons/crm_phonecall_category/i18n/id.po
odoo_addons/crm_phonecall_category/i18n/it.po
odoo_addons/crm_phonecall_category/i18n/ja.po
odoo_addons/crm_phonecall_category/i18n/ko.po
odoo_addons/crm_phonecall_category/i18n/lt.po
odoo_addons/crm_phonecall_category/i18n/lv.po
odoo_addons/crm_phonecall_category/i18n/mk.po
odoo_addons/crm_phonecall_category/i18n/mn.po
